magent_ui/__init__.py
magent_ui/app.py
magent_ui/config.py
magent_ui/utils.py
magent_ui/routers/__init__.py
magent_ui/routers/main.py
magent_ui/routers/agents/__init__.py
magent_ui/routers/agents/router.py
magent_ui/routers/common/__init__.py
magent_ui/routers/common/router.py
magent_ui/routers/knowledge/__init__.py
magent_ui/routers/knowledge/router.py
magent_ui/routers/llms/__init__.py
magent_ui/routers/llms/router.py
magent_ui/routers/plugins/__init__.py
magent_ui/routers/plugins/router.py
magent_ui/routers/resource/__init__.py
magent_ui/routers/resource/router.py
magent_ui/routers/sessions/__init__.py
magent_ui/routers/sessions/router.py
magent_ui/routers/test/__init__.py
magent_ui/routers/test/router.py
magent_ui/routers/tools/__init__.py
magent_ui/routers/tools/router.py
magent_ui/routers/workflow/__init__.py
magent_ui/routers/workflow/router.py
magent_ui/static/232.async.js
magent_ui/static/377.async.js
magent_ui/static/538.chunk.css
magent_ui/static/539.async.js
magent_ui/static/654.async.js
magent_ui/static/745.async.js
magent_ui/static/786.async.js
magent_ui/static/892.async.js
magent_ui/static/976.async.js
magent_ui/static/favicon.ico
magent_ui/static/index.html
magent_ui/static/preload_helper.js
magent_ui/static/umi.css
magent_ui/static/umi.js
magent_ui/static/static/brand.df82773f.jpg
magent_ui/static/static/devopicons.3c46801a.woff2
magent_ui/static/static/file-icons.2cbb51ef.woff2
magent_ui/static/static/fontawesome-webfont.2b13baa7.eot
magent_ui/static/static/fontawesome-webfont.8a7cb27d.ttf
magent_ui/static/static/fontawesome-webfont.cf011583.woff
magent_ui/static/static/fontawesome-webfont.e9955780.woff2
magent_ui/static/static/fontawesome-webfont.f05dad85.svg
magent_ui/static/static/fontawesome.e9955780.woff2
magent_ui/static/static/mfixx.8e0807ce.woff2
magent_ui/static/static/octicons.c982f59d.woff2
magent_ui/templates/index.html
magent_ui/test/locustfile.py
magent_ui-0.1.17.dist-info/METADATA
magent_ui-0.1.17.dist-info/WHEEL
magent_ui-0.1.17.dist-info/RECORD
