Metadata-Version: 2.3
Name: magent-ui
Version: 0.1.17
Author-email: brokun <brokun0128@gmail.com>, shiyu <dongyuxin.dyx@antgroup.com>, sunshinesmilelk <1176136681@qq.com>
Requires-Python: >=3.10
Requires-Dist: aiofiles>=24.1.0
Requires-Dist: jinja2>=3.1.4
Requires-Dist: python-multipart>=0.0.9
Requires-Dist: sse-starlette>=2.1.2
